{
  "main": {
    "id": "a049ade1f4f83302",
    "type": "split",
    "children": [
      {
        "id": "3318eeaffa46fb85",
        "type": "tabs",
        "children": [
          {
            "id": "a7577259dbfc96a5",
            "type": "leaf",
            "state": {
              "type": "markdown",
              "state": {
                "file": "_posts/Linux/Linux_Shell编程.md",
                "mode": "source",
                "source": false
              },
              "icon": "lucide-file",
              "title": "Linux_Shell编程"
            }
          }
        ]
      }
    ],
    "direction": "vertical"
  },
  "left": {
    "id": "c064bebae56b2a6d",
    "type": "split",
    "children": [
      {
        "id": "b5761291f9c055b0",
        "type": "tabs",
        "children": [
          {
            "id": "0322506420835105",
            "type": "leaf",
            "state": {
              "type": "file-explorer",
              "state": {
                "sortOrder": "alphabetical",
                "autoReveal": false
              },
              "icon": "lucide-folder-closed",
              "title": "文件列表"
            }
          },
          {
            "id": "47f3e1488a9f65b4",
            "type": "leaf",
            "state": {
              "type": "outline",
              "state": {
                "file": "_posts/Linux/Linux_Shell编程.md",
                "followCursor": false,
                "showSearch": false,
                "searchQuery": ""
              },
              "icon": "lucide-list",
              "title": "Linux_Shell编程 的大纲"
            }
          },
          {
            "id": "94a98bf8f87560f9",
            "type": "leaf",
            "state": {
              "type": "search",
              "state": {
                "query": "环境变量",
                "matchingCase": false,
                "explainSearch": false,
                "collapseAll": true,
                "extraContext": false,
                "sortOrder": "alphabetical"
              },
              "icon": "lucide-search",
              "title": "搜索"
            }
          },
          {
            "id": "3b33045e582be91e",
            "type": "leaf",
            "state": {
              "type": "bookmarks",
              "state": {},
              "icon": "lucide-bookmark",
              "title": "书签"
            }
          }
        ]
      }
    ],
    "direction": "horizontal",
    "width": 323.5
  },
  "right": {
    "id": "92cce314d83f3e17",
    "type": "split",
    "children": [
      {
        "id": "1d20fd7b57b42c08",
        "type": "tabs",
        "children": [
          {
            "id": "e940c871be9325d3",
            "type": "leaf",
            "state": {
              "type": "backlink",
              "state": {
                "file": "_posts/操作系统/Windows_网络模型.md",
                "collapseAll": false,
                "extraContext": false,
                "sortOrder": "alphabetical",
                "showSearch": false,
                "searchQuery": "",
                "backlinkCollapsed": false,
                "unlinkedCollapsed": true
              },
              "icon": "links-coming-in",
              "title": "Windows_网络模型 的反向链接列表"
            }
          },
          {
            "id": "b6b5f672bb55bbfd",
            "type": "leaf",
            "state": {
              "type": "outgoing-link",
              "state": {
                "file": "_posts/操作系统/Windows_网络模型.md",
                "linksCollapsed": false,
                "unlinkedCollapsed": true
              },
              "icon": "links-going-out",
              "title": "Windows_网络模型 的出链列表"
            }
          },
          {
            "id": "e031e0b0ebc3e118",
            "type": "leaf",
            "state": {
              "type": "tag",
              "state": {
                "sortOrder": "frequency",
                "useHierarchy": true
              },
              "icon": "lucide-tags",
              "title": "标签"
            }
          }
        ],
        "currentTab": 1
      }
    ],
    "direction": "horizontal",
    "width": 300,
    "collapsed": true
  },
  "left-ribbon": {
    "hiddenItems": {
      "switcher:打开快速切换": false,
      "graph:查看关系图谱": false,
      "canvas:新建白板": false,
      "daily-notes:打开/创建今天的日记": false,
      "templates:插入模板": false,
      "command-palette:打开命令面板": false
    }
  },
  "active": "a7577259dbfc96a5",
  "lastOpenFiles": [
    "_posts/Linux/Linux_启动过程.md",
    "images/Linux_启动过程/image-20250715234246004.png",
    "images/Linux_启动过程/image-20250715233203947.png",
    "images/Linux_启动过程/image-20250715232614864.png",
    "images/Linux_启动过程",
    "_posts/Linux/Linux_地址映射.md",
    "_posts/Linux/Linux_配置VSCode.md",
    "_posts/Linux/Linux_设置系统运行级别.md",
    "_posts/Linux/Linux_Ubuntu配置.md",
    "_posts/Linux/Linux_Shell编程.md",
    "_posts/Linux/Linux_vimrc.md",
    "_posts/Linux/Linux_三剑客.md",
    "_posts/Linux/Linux_切换源.md",
    "_posts/Linux/Linux_初识Linux.md",
    "_posts/Linux/Linux_墙的配置.md",
    "_posts/Linux/Linux_守护进程.md",
    "_posts/Linux/Linux_库.md",
    "_posts/Linux/Linux_忘记root密码.md",
    "_posts/Linux/Linux_线程.md",
    "_posts/Linux/Linux_环境配置.md",
    "_posts/Linux/Linux_信号.md",
    "_posts/Linux/Linux_exit.md",
    "_posts/Linux/Linux_vim积累.md",
    "_posts/Linux/Linux_进程.md",
    "_posts/Linux/Linux_vim_.命令.md",
    "_posts/Linux/Linux_libevent_Reactor模式.md",
    "_posts/Linux/Linux_系统调用.md",
    "_posts/Linux/Linux_网络.md",
    "_posts/Linux/Linux_切换系统运行级别.md",
    "images/Cpp11多线程编程_复习/image-20250714195038734.png",
    "images/Cpp11多线程编程_复习/image-20250714151706860.png",
    "images/Cpp11多线程编程_复习/image-20250714144737398.png",
    "images/Cpp11多线程编程_复习/image-20250714142050094.png",
    "images/Cpp11多线程编程_复习/image-20250714141622256.png",
    "images/Cpp11多线程编程_复习/image-20250714141601405.png",
    "images/Cpp11多线程编程_复习",
    "images/mprpc_rpc框架/image-20250713174949860.png",
    "images/mprpc_rpc框架",
    "images/mprpc_protobuf",
    "images/SSH连接",
    "images/01_数组_03_非递减数组的平方",
    "images/刷题_二分查找",
    "images/并查集",
    "images/Cpp_流式IO处理",
    "images/高级数据结构_B树家庭"
  ]
}